awsie/__init__.py
awsie/cli.py
awsie-0.4.3.dist-info/LICENSE
awsie-0.4.3.dist-info/METADATA
awsie-0.4.3.dist-info/WHEEL
awsie-0.4.3.dist-info/entry_points.txt
awsie-0.4.3.dist-info/top_level.txt
awsie-0.4.3.dist-info/RECORD
